{"userName":"wojciechpyzel1","accessKey":"mqss9RvmkH7jkNayEr6m","framework":"playwright","platforms":[{"deviceName":"Samsung Galaxy S23 Ultra","browserName":"chrome","osVersion":13}],"browserstackLocal":true,"buildName":"bstack-demo","buildIdentifier":"5","projectName":"BrowserStack Sample","testObservability":true,"debug":true,"consoleLogs":"info","testContextOptions":{"skipSessionStatus":false},"parallelsPerPlatform":1,"browserStackLocalOptions":{"localIdentifier":"26_Mar_1846_DESKTOP-5B7SS0I_3jvn"},"proxySettings":{}}